opentelemetry/instrumentation/digma/flask/__init__.py
opentelemetry/instrumentation/digma/flask/version.py
opentelemetry_instrumentation_digma_flask-0.2.2.dist-info/LICENSE
opentelemetry_instrumentation_digma_flask-0.2.2.dist-info/METADATA
opentelemetry_instrumentation_digma_flask-0.2.2.dist-info/WHEEL
opentelemetry_instrumentation_digma_flask-0.2.2.dist-info/top_level.txt
opentelemetry_instrumentation_digma_flask-0.2.2.dist-info/RECORD
