Metadata-Version: 2.1
Name: opentelemetry-instrumentation-digma-flask
Version: 0.2.2
Summary: Digma instrumentation for Flask
Home-page: https://github.com/digma-ai/opentelemetry-instrumentation-digma-flask
Author: Roni Dover
Author-email: rdover@digma.ai
Project-URL: Bug Reports, https://github.com/digma-ai/opentelemetry-instrumentation-digma-flask/issues
Project-URL: Source, https://github.com/digma-ai/opentelemetry-instrumentation-digma-flask
Classifier: Programming Language :: Python :: 3
Classifier: Intended Audience :: Developers
Classifier: License :: OSI Approved :: MIT License
Classifier: Natural Language :: English
Classifier: Operating System :: OS Independent
Requires-Python: >=3.6
License-File: LICENSE
Requires-Dist: flask
Requires-Dist: opentelemetry-instrumentation-flask
Requires-Dist: opentelemetry-exporter-otlp
Requires-Dist: opentelemetry-sdk
Requires-Dist: opentelemetry-instrumentation-digma
